zenberry/__init__.py
zenberry/zenberry.py
zenberry-0.1.1.dist-info/LICENSE
zenberry-0.1.1.dist-info/METADATA
zenberry-0.1.1.dist-info/WHEEL
zenberry-0.1.1.dist-info/top_level.txt
zenberry-0.1.1.dist-info/RECORD
